CHANGES.rst
CONTRIBUTORS.rst
MANIFEST.in
README.rst
setup.cfg
setup.py
docs/LICENSE.GPL
docs/LICENSE.txt
src/sc/__init__.py
src/sc.blog.egg-info/PKG-INFO
src/sc.blog.egg-info/SOURCES.txt
src/sc.blog.egg-info/dependency_links.txt
src/sc.blog.egg-info/entry_points.txt
src/sc.blog.egg-info/namespace_packages.txt
src/sc.blog.egg-info/not-zip-safe
src/sc.blog.egg-info/requires.txt
src/sc.blog.egg-info/top_level.txt
src/sc/blog/__init__.py
src/sc/blog/config.py
src/sc/blog/configure.zcml
src/sc/blog/content.py
src/sc/blog/interfaces.py
src/sc/blog/testing.py
src/sc/blog/browser/__init__.py
src/sc/blog/browser/blog.py
src/sc/blog/browser/configure.zcml
src/sc/blog/browser/templates/blogheader.pt
src/sc/blog/browser/templates/folder_full_view.pt
src/sc/blog/browser/templates/folder_summary_view.pt
src/sc/blog/locales/manual.pot
src/sc/blog/locales/plone.pot
src/sc/blog/locales/sc.blog.pot
src/sc/blog/locales/es/LC_MESSAGES/plone.po
src/sc/blog/locales/es/LC_MESSAGES/sc.blog.po
src/sc/blog/locales/pt_BR/LC_MESSAGES/plone.po
src/sc/blog/locales/pt_BR/LC_MESSAGES/sc.blog.po
src/sc/blog/profiles/default/browserlayer.xml
src/sc/blog/profiles/default/metadata.xml
src/sc/blog/profiles/default/rolemap.xml
src/sc/blog/profiles/default/types.xml
src/sc/blog/profiles/default/viewlets.xml
src/sc/blog/profiles/default/types/Blog.xml
src/sc/blog/static/blog-icon.png
src/sc/blog/tests/__init__.py
src/sc/blog/tests/test_blog.robot
src/sc/blog/tests/test_content.py
src/sc/blog/tests/test_robot.py
src/sc/blog/tests/test_setup.py
src/sc/blog/tests/test_viewlet.py
src/sc/blog/tests/test_views.py