Metadata-Version: 1.1
Name: sc.blog
Version: 1.1b1
Summary: A content type describing a blog.
Home-page: https://github.com/simplesconsultoria/sc.blog
Author: Simples Consultoria
Author-email: products@simplesconsultoria.com.br
License: GPLv2
Keywords: plone dexterity blog
Platform: UNKNOWN
Classifier: Development Status :: 4 - Beta
Classifier: Environment :: Web Environment
Classifier: Framework :: Plone
Classifier: Framework :: Plone :: 4.2
Classifier: Framework :: Plone :: 4.3
Classifier: Intended Audience :: End Users/Desktop
Classifier: Intended Audience :: System Administrators
Classifier: License :: OSI Approved :: GNU General Public License v2 (GPLv2)
Classifier: Operating System :: OS Independent
Classifier: Programming Language :: JavaScript
Classifier: Programming Language :: Python
Classifier: Programming Language :: Python :: 2.7
Classifier: Topic :: Office/Business :: News/Diary
Classifier: Topic :: Software Development :: Libraries :: Python Modules
